CHANGES.txt
MANIFEST.in
README.txt
setup.py
guillotine/__init__.py
guillotine/tests.py
guillotine.egg-info/PKG-INFO
guillotine.egg-info/SOURCES.txt
guillotine.egg-info/dependency_links.txt
guillotine.egg-info/entry_points.txt
guillotine.egg-info/not-zip-safe
guillotine.egg-info/top_level.txt