Metadata-Version: 1.0
Name: guillotine
Version: 0.1
Summary: A middleware for proper handling of HEAD requests.
Home-page: http://pylonsproject.org
Author: Chris Rossi
Author-email: pylons-devel@googlegroups.com
License: BSD-derived (http://www.repoze.org/LICENSE.txt)
Keywords: web wsgi middleware
Platform: UNKNOWN
Classifier: Intended Audience :: Developers
Classifier: Programming Language :: Python
Classifier: Topic :: Internet :: WWW/HTTP
Classifier: Topic :: Internet :: WWW/HTTP :: WSGI
Classifier: License :: Repoze Public License
